{
  "access": [
    "public",
    "super"
  ],
  "annotations": [],
  "bootstrapmethods": [],
  "enclosingmethod": null,
  "fields": [],
  "innerclasses": [],
  "interfaces": [],
  "methods": [
    {
      "access": [
        "public"
      ],
      "annotations": [],
      "code": {
        "annotations": [],
        "bytecode": [
          {
            "index": 0,
            "offset": 0,
            "opr": "load",
            "type": "ref"
          },
          {
            "access": "special",
            "method": {
              "args": [],
              "is_interface": false,
              "name": "<init>",
              "ref": {
                "kind": "class",
                "name": "java/lang/Object"
              },
              "returns": null
            },
            "offset": 1,
            "opr": "invoke"
          },
          {
            "offset": 4,
            "opr": "return",
            "type": null
          }
        ],
        "exceptions": [],
        "lines": [
          {
            "line": 3,
            "offset": 0
          }
        ],
        "max_locals": 1,
        "max_stack": 1,
        "stack_map": null
      },
      "default": null,
      "exceptions": [],
      "name": "<init>",
      "params": [],
      "returns": {
        "annotations": [],
        "type": null
      },
      "typeparams": []
    },
    {
      "access": [
        "public"
      ],
      "annotations": [],
      "code": {
        "annotations": [],
        "bytecode": [
          {
            "field": {
              "class": "java/lang/System",
              "name": "out",
              "type": {
                "kind": "class",
                "name": "java/io/PrintStream"
              }
            },
            "offset": 0,
            "opr": "get",
            "static": true
          },
          {
            "offset": 3,
            "opr": "push",
            "value": {
              "type": "string",
              "value": "Another Method"
            }
          },
          {
            "access": "virtual",
            "method": {
              "args": [
                {
                  "kind": "class",
                  "name": "java/lang/String"
                }
              ],
              "name": "println",
              "ref": {
                "kind": "class",
                "name": "java/io/PrintStream"
              },
              "returns": null
            },
            "offset": 5,
            "opr": "invoke"
          },
          {
            "index": 0,
            "offset": 8,
            "opr": "load",
            "type": "ref"
          },
          {
            "access": "virtual",
            "method": {
              "args": [],
              "name": "yetAnotherMethod",
              "ref": {
                "kind": "class",
                "name": "jpamb/cases/syntaxer/SyntaxerTestOther"
              },
              "returns": null
            },
            "offset": 9,
            "opr": "invoke"
          },
          {
            "offset": 12,
            "opr": "return",
            "type": null
          }
        ],
        "exceptions": [],
        "lines": [
          {
            "line": 6,
            "offset": 0
          },
          {
            "line": 7,
            "offset": 3
          },
          {
            "line": 8,
            "offset": 5
          }
        ],
        "max_locals": 1,
        "max_stack": 2,
        "stack_map": null
      },
      "default": null,
      "exceptions": [],
      "name": "anotherMethod",
      "params": [],
      "returns": {
        "annotations": [],
        "type": null
      },
      "typeparams": []
    },
    {
      "access": [
        "public"
      ],
      "annotations": [],
      "code": {
        "annotations": [],
        "bytecode": [
          {
            "field": {
              "class": "java/lang/System",
              "name": "out",
              "type": {
                "kind": "class",
                "name": "java/io/PrintStream"
              }
            },
            "offset": 0,
            "opr": "get",
            "static": true
          },
          {
            "offset": 3,
            "opr": "push",
            "value": {
              "type": "string",
              "value": "Yet Another Method"
            }
          },
          {
            "access": "virtual",
            "method": {
              "args": [
                {
                  "kind": "class",
                  "name": "java/lang/String"
                }
              ],
              "name": "println",
              "ref": {
                "kind": "class",
                "name": "java/io/PrintStream"
              },
              "returns": null
            },
            "offset": 5,
            "opr": "invoke"
          },
          {
            "offset": 8,
            "opr": "return",
            "type": null
          }
        ],
        "exceptions": [],
        "lines": [
          {
            "line": 11,
            "offset": 0
          },
          {
            "line": 12,
            "offset": 3
          }
        ],
        "max_locals": 1,
        "max_stack": 2,
        "stack_map": null
      },
      "default": null,
      "exceptions": [],
      "name": "yetAnotherMethod",
      "params": [],
      "returns": {
        "annotations": [],
        "type": null
      },
      "typeparams": []
    }
  ],
  "name": "jpamb/cases/syntaxer/SyntaxerTestOther",
  "super": {
    "annotations": [],
    "args": [],
    "inner": null,
    "name": "java/lang/Object"
  },
  "typeparams": [],
  "version": [
    65,
    0
  ]
}